LICENSE.txt
MANIFEST.in
README.rst
setup.py
examples/__init__.py
examples/baike_example.py
examples/mail_example.py
examples/ping_scan_example.py
examples/spider_example.py
examples/webimage_example.py
jojo_net.egg-info/PKG-INFO
jojo_net.egg-info/SOURCES.txt
jojo_net.egg-info/dependency_links.txt
jojo_net.egg-info/requires.txt
jojo_net.egg-info/top_level.txt
net/__init__.py
net/binary.py
net/dns.py
net/http.py
net/mail.py
net/remote.py
net/scan.py
net/spider.py
net/util.py
net/webapi.py
net/doc/net.rst
net/examples/__init__.py
net/examples/baike_example.py
net/examples/mail_example.py
net/examples/ping_scan_example.py
net/examples/spider_example.py
net/examples/webimage_example.py
net/test/__init__.py
net/test/test_binary.py
net/test/test_dns.py
net/test/test_dnsclient.py
net/test/test_dnsserver.py
net/test/test_scan.py
net/test/test_spider.py
test/__init__.py
test/test_scan.py